["index.md",{"file":"유비무환-korean-4-letter-words-1.md","name":"유비무환 - Korean 4 Character Idioms(사자성어) #1"},{"file":"대기만성-korean-4-letter-words-2.md","name":"대기만성 - Korean 4 Character Idioms(사자성어) #2"},{"file":"좌지우지-korean-4-letter-words-3.md","name":"좌지우지 - Korean 4 Character Idioms(사자성어) #3"},{"file":"금시초문-korean-4-letter-words-4.md","name":"금시초문 - Korean 4 Character Idioms(사자성어) #4"},{"file":"일취월장-korean-4-letter-words-5.md","name":"일취월장 - Korean 4 Character Idioms(사자성어) #5"},{"file":"속수무책-korean-4-character-idioms-6.md","name":"속수무책 - Korean 4 Character Idioms(사자성어) #6"},{"file":"자업자득-korean-4-character-idioms-7.md","name":"자업자득 - Korean 4 Character Idioms(사자성어) #7"},{"file":"우왕좌왕-korean-4-character-idioms-8.md","name":"우왕좌왕 - Korean 4 Character Idioms #8"},{"file":"설상가상-korean-4-character-idioms-9.md","name":"설상가상 - Korean 4 Character Idioms #9"},{"file":"상전벽해-korean-4-character-idioms.md","name":"상전벽해 - Korean 4 Character Idioms #10"},{"file":"단도직입-korean-4-character-idioms-11.md","name":"단도직입 - Korean 4 Character Idioms #11"},{"file":"동분서주東奔西走-korean-4-character-idioms-12.md","name":"동분서주(東奔西走) - Korean 4 Character Idioms #12"},{"file":"심사숙고-korean-4-character-idioms-13.md","name":"심사숙고(深思熟考) - Korean 4 Character Idioms #13"},{"file":"난공불락難攻不落-korean-4-character-idioms-14.md","name":"난공불락(難攻不落) - Korean 4 Character Idioms #14"},{"file":"천군만마千軍萬馬-korean-4-character-idioms-15.md","name":"천군만마(千軍萬馬) - Korean 4 Character Idioms #15"},{"file":"새옹지마塞翁之馬-korean-4-character-idioms.md","name":"새옹지마(塞翁之馬) - Korean 4 Character Idioms"},{"file":"일사천리一瀉千里-korean-4-character-idioms-17.md","name":"일사천리(一瀉千里) - Korean 4 Character Idioms #17"},{"file":"금상첨화錦上添花-korean-4-character-idioms-18.md","name":"금상첨화(錦上添花) - Korean 4 Character Idioms #18"},{"file":"반신반의半信半疑-korean-4-character-idioms-19.md","name":"반신반의(半信半疑) - Korean 4 Character Idioms #19"},{"file":"고진감래苦盡甘來-korean-4-character-idioms-20.md","name":"고진감래(苦盡甘來) - Korean 4 Character Idioms #20"},{"file":"작심삼일作心三日-korean-4-character-idioms-21.md","name":"작심삼일(作心三日) - Korean 4 Character Idioms #21"},{"file":"좌충우돌左衝右突-korean-4-character-idioms-22.md","name":"좌충우돌(左衝右突) - Korean 4 Character Idioms #22"},{"file":"개과천선-korean-4-character-idioms-23.md","name":"개과천선 - Korean 4 Character Idioms #23"},{"file":"금의환향錦衣還鄕-korean-4-character-idioms-24.md","name":"금의환향(錦衣還鄕) - Korean 4 Character Idioms #24"},{"file":"물심양면物心兩面-korean-4-character-idioms-25.md","name":"물심양면(物心兩面) - Korean 4 Character Idioms #25"},{"file":"선견지명先見之明-korean-4-character-idioms-27.md","name":"선견지명(先見之明) - Korean 4 Character Idioms #26"},{"file":"근묵자흑近墨者黑-korean-4-character-idioms-27.md","name":"근묵자흑(近墨者黑) - Korean 4 Character Idioms #27"},{"file":"팔방미인八方美人-korean-4-character-idioms.md","name":"팔방미인(八方美人) - Korean 4 Character Idioms"},{"file":"정정당당正正堂堂-korean-4-character-idioms-29.md","name":"정정당당(正正堂堂) - Korean 4 Character Idioms #29"},{"file":"시종일관始終一貫-korean-4-character-idioms-30.md","name":"시종일관(始終一貫) - Korean 4 Character Idioms #30"},{"file":"사자성어-vs-고사성어-vs-한자성어.md","name":"사자성어 vs. 고사성어 vs. 한자성어"}]